__init__.py
firewall_handler.py
main.py
gpx_kml_converter/__init__.py
gpx_kml_converter/__main__.py
gpx_kml_converter/_version.py
gpx_kml_converter/cli/__init__.py
gpx_kml_converter/cli/__main__.py
gpx_kml_converter/cli/cli.py
gpx_kml_converter/config/__init__.py
gpx_kml_converter/config/config.py
gpx_kml_converter/core/__init__.py
gpx_kml_converter/core/base.py
gpx_kml_converter/core/gpx_file.py
gpx_kml_converter/core/gpx_plotter.py
gpx_kml_converter/core/logging.py
gpx_kml_converter/gui/__init__.py
gpx_kml_converter/gui/__main__.py
gpx_kml_converter/gui/gui.py
gpx_kml_converter/gui/tool_tip.py
gpx_kml_converter-1.0.5.dist-info/licenses/LICENSE
gpx_kml_converter-1.0.5.dist-info/METADATA
gpx_kml_converter-1.0.5.dist-info/WHEEL
gpx_kml_converter-1.0.5.dist-info/entry_points.txt
gpx_kml_converter-1.0.5.dist-info/top_level.txt
gpx_kml_converter-1.0.5.dist-info/RECORD
